{
  "nodes": {
    "SitePage /dev-404-page/": {
      "path": "/dev-404-page/",
      "id": "SitePage /dev-404-page/",
      "parent": "SOURCE",
      "children": [],
      "internal": {
        "type": "SitePage",
        "contentDigest": "f91d29e10ba680b413138cf9ed86e655",
        "owner": "internal-data-bridge"
      }
    },
    "d48d1c52-fe48-53cb-8f08-aa4b47dde5a5": {
      "resolve": "/Users/macbook_pro/Documents/www/self/stefirkp.github.io/node_modules/gatsby/dist/internal-plugins/dev-404-page",
      "id": "d48d1c52-fe48-53cb-8f08-aa4b47dde5a5",
      "name": "dev-404-page",
      "version": "1.0.0",
      "pluginOptions": {
        "plugins": []
      },
      "nodeAPIs": [
        "createPagesStatefully"
      ],
      "browserAPIs": [],
      "ssrAPIs": [],
      "pluginFilepath": "/Users/macbook_pro/Documents/www/self/stefirkp.github.io/node_modules/gatsby/dist/internal-plugins/dev-404-page",
      "packageJson": {
        "name": "dev-404-page",
        "description": "Internal plugin to add a 404 page in development with helpful information",
        "version": "1.0.0",
        "main": "index.js",
        "author": "Kyle Mathews <mathews.kyle@gmail.com>",
        "license": "MIT",
        "dependencies": [],
        "devDependencies": [],
        "peerDependencies": [],
        "optionalDependecies": [],
        "bundledDependecies": []
      },
      "parent": "SOURCE",
      "children": [],
      "internal": {
        "contentDigest": "06a0a59b25b29e7955d13fff58ddc62f",
        "type": "SitePlugin",
        "owner": "internal-data-bridge"
      }
    },
    "1fc32581-893a-55e8-8927-bcd667e2b700": {
      "resolve": "/Users/macbook_pro/Documents/www/self/stefirkp.github.io/node_modules/gatsby/dist/internal-plugins/load-babel-config",
      "id": "1fc32581-893a-55e8-8927-bcd667e2b700",
      "name": "load-babel-config",
      "version": "1.0.0",
      "pluginOptions": {
        "plugins": []
      },
      "nodeAPIs": [
        "onPreBootstrap"
      ],
      "browserAPIs": [],
      "ssrAPIs": [],
      "pluginFilepath": "/Users/macbook_pro/Documents/www/self/stefirkp.github.io/node_modules/gatsby/dist/internal-plugins/load-babel-config",
      "packageJson": {
        "name": "load-babel-config",
        "description": "Internal plugin that handles loading Babel configs",
        "version": "1.0.0",
        "main": "index.js",
        "author": "Kyle Mathews <mathews.kyle@gmail.com>",
        "license": "MIT",
        "dependencies": [],
        "devDependencies": [],
        "peerDependencies": [],
        "optionalDependecies": [],
        "bundledDependecies": []
      },
      "parent": "SOURCE",
      "children": [],
      "internal": {
        "contentDigest": "40d4f689e6c3e63d519015c2e2c39010",
        "type": "SitePlugin",
        "owner": "internal-data-bridge"
      }
    },
    "a5079d69-ba80-53dc-82f9-0f440bd5448c": {
      "resolve": "/Users/macbook_pro/Documents/www/self/stefirkp.github.io/node_modules/gatsby/dist/internal-plugins/internal-data-bridge",
      "id": "a5079d69-ba80-53dc-82f9-0f440bd5448c",
      "name": "internal-data-bridge",
      "version": "1.0.0",
      "pluginOptions": {
        "plugins": []
      },
      "nodeAPIs": [
        "sourceNodes",
        "onCreatePage"
      ],
      "browserAPIs": [],
      "ssrAPIs": [],
      "pluginFilepath": "/Users/macbook_pro/Documents/www/self/stefirkp.github.io/node_modules/gatsby/dist/internal-plugins/internal-data-bridge",
      "packageJson": {
        "name": "internal-data-bridge",
        "description": "An internal Gatsby plugin which creates data nodes from internal data",
        "version": "1.0.0",
        "main": "index.js",
        "author": "Kyle Mathews <mathews.kyle@gmail.com>",
        "license": "MIT",
        "dependencies": [],
        "devDependencies": [],
        "peerDependencies": [],
        "optionalDependecies": [],
        "bundledDependecies": []
      },
      "parent": "SOURCE",
      "children": [],
      "internal": {
        "contentDigest": "62bf2b72a04b1660a97dc81c919d1251",
        "type": "SitePlugin",
        "owner": "internal-data-bridge"
      }
    },
    "f795702c-a3b8-5a88-88ee-5d06019d44fa": {
      "resolve": "/Users/macbook_pro/Documents/www/self/stefirkp.github.io/node_modules/gatsby/dist/internal-plugins/prod-404",
      "id": "f795702c-a3b8-5a88-88ee-5d06019d44fa",
      "name": "prod-404",
      "version": "1.0.0",
      "pluginOptions": {
        "plugins": []
      },
      "nodeAPIs": [
        "onCreatePage"
      ],
      "browserAPIs": [],
      "ssrAPIs": [],
      "pluginFilepath": "/Users/macbook_pro/Documents/www/self/stefirkp.github.io/node_modules/gatsby/dist/internal-plugins/prod-404",
      "packageJson": {
        "name": "prod-404",
        "description": "Internal plugin to detect various flavors of 404 pages and ensure there's a 404.html path created as well to ensure compatability with static hosts",
        "version": "1.0.0",
        "main": "index.js",
        "author": "Kyle Mathews <mathews.kyle@gmail.com>",
        "license": "MIT",
        "dependencies": [],
        "devDependencies": [],
        "peerDependencies": [],
        "optionalDependecies": [],
        "bundledDependecies": []
      },
      "parent": "SOURCE",
      "children": [],
      "internal": {
        "contentDigest": "e5201e7c64b6cc7dbec0e95be1226684",
        "type": "SitePlugin",
        "owner": "internal-data-bridge"
      }
    },
    "84dad27f-1d44-51fc-ac56-4db2e5222995": {
      "resolve": "/Users/macbook_pro/Documents/www/self/stefirkp.github.io/node_modules/gatsby/dist/internal-plugins/query-runner",
      "id": "84dad27f-1d44-51fc-ac56-4db2e5222995",
      "name": "query-runner",
      "version": "1.0.0",
      "pluginOptions": {
        "plugins": []
      },
      "nodeAPIs": [
        "onCreatePage"
      ],
      "browserAPIs": [],
      "ssrAPIs": [],
      "pluginFilepath": "/Users/macbook_pro/Documents/www/self/stefirkp.github.io/node_modules/gatsby/dist/internal-plugins/query-runner",
      "packageJson": {
        "name": "query-runner",
        "description": "Internal plugin for running queries",
        "version": "1.0.0",
        "main": "index.js",
        "author": "",
        "license": "MIT",
        "dependencies": [],
        "devDependencies": [],
        "peerDependencies": [],
        "optionalDependecies": [],
        "bundledDependecies": []
      },
      "parent": "SOURCE",
      "children": [],
      "internal": {
        "contentDigest": "fda84ea54a1cff4e23f94795ea39738d",
        "type": "SitePlugin",
        "owner": "internal-data-bridge"
      }
    },
    "1943ff2f-9c0c-558d-8d0c-006603e8106a": {
      "resolve": "/Users/macbook_pro/Documents/www/self/stefirkp.github.io/node_modules/gatsby-plugin-react-helmet",
      "id": "1943ff2f-9c0c-558d-8d0c-006603e8106a",
      "name": "gatsby-plugin-react-helmet",
      "version": "3.0.2",
      "pluginOptions": {
        "plugins": []
      },
      "nodeAPIs": [],
      "browserAPIs": [],
      "ssrAPIs": [
        "onRenderBody"
      ],
      "pluginFilepath": "/Users/macbook_pro/Documents/www/self/stefirkp.github.io/node_modules/gatsby-plugin-react-helmet",
      "packageJson": {
        "name": "gatsby-plugin-react-helmet",
        "description": "Manage document head data with react-helmet. Provides drop-in server rendering support for Gatsby.",
        "version": "3.0.2",
        "main": "index.js",
        "keywords": [
          "gatsby",
          "gatsby-plugin",
          "favicon",
          "react-helmet",
          "seo",
          "document",
          "head",
          "title",
          "meta",
          "link",
          "script",
          "base",
          "noscript",
          "style"
        ],
        "author": {
          "name": "Kyle Mathews",
          "email": "matthews.kyle@gmail.com"
        },
        "license": "MIT",
        "dependencies": [
          {
            "name": "@babel/runtime",
            "version": "^7.0.0"
          }
        ],
        "devDependencies": [
          {
            "name": "@babel/cli",
            "version": "^7.0.0"
          },
          {
            "name": "@babel/core",
            "version": "^7.0.0"
          },
          {
            "name": "babel-preset-gatsby-package",
            "version": "^0.1.2"
          },
          {
            "name": "cross-env",
            "version": "^5.1.4"
          }
        ],
        "peerDependencies": [
          {
            "name": "gatsby",
            "version": ">2.0.0-alpha"
          },
          {
            "name": "react-helmet",
            "version": ">=5.1.3"
          }
        ],
        "optionalDependecies": [],
        "bundledDependecies": []
      },
      "parent": "SOURCE",
      "children": [],
      "internal": {
        "contentDigest": "923fb7ce80c18cde6bb8f6c84865f496",
        "type": "SitePlugin",
        "owner": "internal-data-bridge"
      }
    },
    "8f70af98-7ce9-5efe-97fa-8f9c6817f34a": {
      "resolve": "/Users/macbook_pro/Documents/www/self/stefirkp.github.io/node_modules/gatsby-source-filesystem",
      "id": "8f70af98-7ce9-5efe-97fa-8f9c6817f34a",
      "name": "gatsby-source-filesystem",
      "version": "2.0.8",
      "pluginOptions": {
        "plugins": [],
        "name": "images",
        "path": "/Users/macbook_pro/Documents/www/self/stefirkp.github.io/src/images"
      },
      "nodeAPIs": [
        "sourceNodes",
        "setFieldsOnGraphQLNodeType"
      ],
      "browserAPIs": [],
      "ssrAPIs": [],
      "pluginFilepath": "/Users/macbook_pro/Documents/www/self/stefirkp.github.io/node_modules/gatsby-source-filesystem",
      "packageJson": {
        "name": "gatsby-source-filesystem",
        "description": "Gatsby plugin which parses files within a directory for further parsing by other plugins",
        "version": "2.0.8",
        "keywords": [
          "gatsby",
          "gatsby-plugin"
        ],
        "author": {
          "name": "Kyle Mathews",
          "email": "mathews.kyle@gmail.com"
        },
        "license": "MIT",
        "dependencies": [
          {
            "name": "@babel/runtime",
            "version": "^7.0.0"
          },
          {
            "name": "better-queue",
            "version": "^3.8.7"
          },
          {
            "name": "bluebird",
            "version": "^3.5.0"
          },
          {
            "name": "chokidar",
            "version": "^1.7.0"
          },
          {
            "name": "file-type",
            "version": "^10.2.0"
          },
          {
            "name": "fs-extra",
            "version": "^5.0.0"
          },
          {
            "name": "got",
            "version": "^7.1.0"
          },
          {
            "name": "md5-file",
            "version": "^3.1.1"
          },
          {
            "name": "mime",
            "version": "^2.2.0"
          },
          {
            "name": "pretty-bytes",
            "version": "^4.0.2"
          },
          {
            "name": "read-chunk",
            "version": "^3.0.0"
          },
          {
            "name": "slash",
            "version": "^1.0.0"
          },
          {
            "name": "valid-url",
            "version": "^1.0.9"
          },
          {
            "name": "xstate",
            "version": "^3.1.0"
          }
        ],
        "devDependencies": [
          {
            "name": "@babel/cli",
            "version": "^7.0.0"
          },
          {
            "name": "@babel/core",
            "version": "^7.0.0"
          },
          {
            "name": "babel-preset-gatsby-package",
            "version": "^0.1.2"
          },
          {
            "name": "cross-env",
            "version": "^5.1.4"
          }
        ],
        "peerDependencies": [
          {
            "name": "gatsby",
            "version": ">2.0.0-alpha"
          }
        ],
        "optionalDependecies": [],
        "bundledDependecies": []
      },
      "parent": "SOURCE",
      "children": [],
      "internal": {
        "contentDigest": "28c254b5aff4e8b3804d066a94031619",
        "type": "SitePlugin",
        "owner": "internal-data-bridge"
      }
    },
    "da3d06eb-685e-5c77-ae1d-750eb6a2e4a9": {
      "resolve": "/Users/macbook_pro/Documents/www/self/stefirkp.github.io/node_modules/gatsby-transformer-sharp",
      "id": "da3d06eb-685e-5c77-ae1d-750eb6a2e4a9",
      "name": "gatsby-transformer-sharp",
      "version": "2.1.8",
      "pluginOptions": {
        "plugins": []
      },
      "nodeAPIs": [
        "onCreateNode",
        "setFieldsOnGraphQLNodeType",
        "onPreExtractQueries"
      ],
      "browserAPIs": [],
      "ssrAPIs": [],
      "pluginFilepath": "/Users/macbook_pro/Documents/www/self/stefirkp.github.io/node_modules/gatsby-transformer-sharp",
      "packageJson": {
        "name": "gatsby-transformer-sharp",
        "description": "Gatsby transformer plugin for images using Sharp",
        "version": "2.1.8",
        "keywords": [
          "gatsby",
          "gatsby-plugin",
          "image",
          "sharp"
        ],
        "author": {
          "name": "Kyle Mathews",
          "email": "mathews.kyle@gmail.com"
        },
        "license": "MIT",
        "dependencies": [
          {
            "name": "@babel/runtime",
            "version": "^7.0.0"
          },
          {
            "name": "bluebird",
            "version": "^3.5.0"
          },
          {
            "name": "fs-extra",
            "version": "^4.0.2"
          },
          {
            "name": "potrace",
            "version": "^2.1.1"
          },
          {
            "name": "probe-image-size",
            "version": "^4.0.0"
          },
          {
            "name": "sharp",
            "version": "^0.21.0"
          }
        ],
        "devDependencies": [
          {
            "name": "@babel/cli",
            "version": "^7.0.0"
          },
          {
            "name": "@babel/core",
            "version": "^7.0.0"
          },
          {
            "name": "babel-preset-gatsby-package",
            "version": "^0.1.2"
          },
          {
            "name": "cross-env",
            "version": "^5.1.4"
          }
        ],
        "peerDependencies": [
          {
            "name": "gatsby",
            "version": "^2.0.33"
          },
          {
            "name": "gatsby-plugin-sharp",
            "version": "^2.0.0-beta.3"
          }
        ],
        "optionalDependecies": [],
        "bundledDependecies": []
      },
      "parent": "SOURCE",
      "children": [],
      "internal": {
        "contentDigest": "0ade377cc79f35e34658720b650cb7f2",
        "type": "SitePlugin",
        "owner": "internal-data-bridge"
      }
    },
    "84d6154d-4241-556c-a679-cc8339cac100": {
      "resolve": "/Users/macbook_pro/Documents/www/self/stefirkp.github.io/node_modules/gatsby-plugin-sharp",
      "id": "84d6154d-4241-556c-a679-cc8339cac100",
      "name": "gatsby-plugin-sharp",
      "version": "2.0.15",
      "pluginOptions": {
        "plugins": []
      },
      "nodeAPIs": [
        "onPreInit"
      ],
      "browserAPIs": [],
      "ssrAPIs": [],
      "pluginFilepath": "/Users/macbook_pro/Documents/www/self/stefirkp.github.io/node_modules/gatsby-plugin-sharp",
      "packageJson": {
        "name": "gatsby-plugin-sharp",
        "description": "Wrapper of the Sharp image manipulation library for Gatsby plugins",
        "version": "2.0.15",
        "main": "index.js",
        "keywords": [
          "gatsby",
          "gatsby-plugin",
          "image",
          "sharp"
        ],
        "author": {
          "name": "Kyle Mathews",
          "email": "mathews.kyle@gmail.com"
        },
        "license": "MIT",
        "dependencies": [
          {
            "name": "@babel/runtime",
            "version": "^7.0.0"
          },
          {
            "name": "async",
            "version": "^2.1.2"
          },
          {
            "name": "bluebird",
            "version": "^3.5.0"
          },
          {
            "name": "fs-exists-cached",
            "version": "^1.0.0"
          },
          {
            "name": "fs-extra",
            "version": "^7.0.0"
          },
          {
            "name": "imagemin",
            "version": "^6.0.0"
          },
          {
            "name": "imagemin-mozjpeg",
            "version": "^7.0.0"
          },
          {
            "name": "imagemin-pngquant",
            "version": "^6.0.0"
          },
          {
            "name": "imagemin-webp",
            "version": "^4.1.0"
          },
          {
            "name": "lodash",
            "version": "^4.17.10"
          },
          {
            "name": "mini-svg-data-uri",
            "version": "^1.0.0"
          },
          {
            "name": "potrace",
            "version": "^2.1.1"
          },
          {
            "name": "probe-image-size",
            "version": "^4.0.0"
          },
          {
            "name": "progress",
            "version": "^1.1.8"
          },
          {
            "name": "sharp",
            "version": "^0.21.0"
          },
          {
            "name": "svgo",
            "version": "^0.7.2"
          }
        ],
        "devDependencies": [
          {
            "name": "@babel/cli",
            "version": "^7.0.0"
          },
          {
            "name": "@babel/core",
            "version": "^7.0.0"
          },
          {
            "name": "babel-preset-gatsby-package",
            "version": "^0.1.3"
          },
          {
            "name": "cross-env",
            "version": "^5.1.4"
          }
        ],
        "peerDependencies": [
          {
            "name": "gatsby",
            "version": ">2.0.0-alpha"
          }
        ],
        "optionalDependecies": [],
        "bundledDependecies": []
      },
      "parent": "SOURCE",
      "children": [],
      "internal": {
        "contentDigest": "d8200d59f6e1e3d496043167f317dbbf",
        "type": "SitePlugin",
        "owner": "internal-data-bridge"
      }
    },
    "112c12f8-b222-509b-abe0-dfe93a905df9": {
      "resolve": "/Users/macbook_pro/Documents/www/self/stefirkp.github.io/node_modules/gatsby-plugin-manifest",
      "id": "112c12f8-b222-509b-abe0-dfe93a905df9",
      "name": "gatsby-plugin-manifest",
      "version": "2.0.9",
      "pluginOptions": {
        "plugins": [],
        "name": "gatsby-starter-default",
        "short_name": "starter",
        "start_url": "/",
        "background_color": "#663399",
        "theme_color": "#663399",
        "display": "minimal-ui",
        "icon": "src/images/gatsby-icon.png"
      },
      "nodeAPIs": [
        "onPostBootstrap"
      ],
      "browserAPIs": [],
      "ssrAPIs": [
        "onRenderBody"
      ],
      "pluginFilepath": "/Users/macbook_pro/Documents/www/self/stefirkp.github.io/node_modules/gatsby-plugin-manifest",
      "packageJson": {
        "name": "gatsby-plugin-manifest",
        "description": "Gatsby plugin which adds a manifest.webmanifest to make sites progressive web apps",
        "version": "2.0.9",
        "main": "index.js",
        "keywords": [
          "gatsby",
          "gatsby-plugin",
          "favicon",
          "icons",
          "manifest.webmanifest",
          "progressive-web-app",
          "pwa"
        ],
        "author": {
          "name": "Kyle Mathews",
          "email": "mathews.kyle@gmail.com"
        },
        "license": "MIT",
        "dependencies": [
          {
            "name": "@babel/runtime",
            "version": "^7.0.0"
          },
          {
            "name": "bluebird",
            "version": "^3.5.0"
          },
          {
            "name": "sharp",
            "version": "^0.21.0"
          }
        ],
        "devDependencies": [
          {
            "name": "@babel/cli",
            "version": "^7.0.0"
          },
          {
            "name": "@babel/core",
            "version": "^7.0.0"
          },
          {
            "name": "babel-preset-gatsby-package",
            "version": "^0.1.2"
          },
          {
            "name": "cross-env",
            "version": "^5.1.4"
          }
        ],
        "peerDependencies": [
          {
            "name": "gatsby",
            "version": ">2.0.0-alpha"
          }
        ],
        "optionalDependecies": [],
        "bundledDependecies": []
      },
      "parent": "SOURCE",
      "children": [],
      "internal": {
        "contentDigest": "d09db1920dbddcb30d7e6720e4fc8997",
        "type": "SitePlugin",
        "owner": "internal-data-bridge"
      }
    },
    "d8f4bf2b-73c7-5c69-93d1-79ac2ac7c2e8": {
      "resolve": "/Users/macbook_pro/Documents/www/self/stefirkp.github.io/node_modules/gatsby-plugin-sass",
      "id": "d8f4bf2b-73c7-5c69-93d1-79ac2ac7c2e8",
      "name": "gatsby-plugin-sass",
      "version": "2.0.7",
      "pluginOptions": {
        "plugins": []
      },
      "nodeAPIs": [
        "onCreateWebpackConfig"
      ],
      "browserAPIs": [],
      "ssrAPIs": [],
      "pluginFilepath": "/Users/macbook_pro/Documents/www/self/stefirkp.github.io/node_modules/gatsby-plugin-sass",
      "packageJson": {
        "name": "gatsby-plugin-sass",
        "description": "Gatsby plugin to handle scss/sass files",
        "version": "2.0.7",
        "main": "index.js",
        "keywords": [
          "gatsby",
          "gatsby-plugin",
          "sass",
          "scss"
        ],
        "author": {
          "name": "Daniel Farrell",
          "email": "daniel@mobelux.com"
        },
        "license": "MIT",
        "dependencies": [
          {
            "name": "@babel/runtime",
            "version": "^7.0.0"
          },
          {
            "name": "sass-loader",
            "version": "^7.0.1"
          }
        ],
        "devDependencies": [
          {
            "name": "@babel/cli",
            "version": "^7.0.0"
          },
          {
            "name": "@babel/core",
            "version": "^7.0.0"
          },
          {
            "name": "babel-preset-gatsby-package",
            "version": "^0.1.3"
          },
          {
            "name": "cross-env",
            "version": "^5.1.4"
          }
        ],
        "peerDependencies": [
          {
            "name": "gatsby",
            "version": ">2.0.0-alpha"
          },
          {
            "name": "node-sass",
            "version": "^4.9.0"
          }
        ],
        "optionalDependecies": [],
        "bundledDependecies": []
      },
      "parent": "SOURCE",
      "children": [],
      "internal": {
        "contentDigest": "08c902739512572274d4d7b71fdca598",
        "type": "SitePlugin",
        "owner": "internal-data-bridge"
      }
    },
    "8eac7c4e-d473-5530-92ee-8cfaa7ee5e37": {
      "resolve": "/Users/macbook_pro/Documents/www/self/stefirkp.github.io/node_modules/gatsby-plugin-prefetch-google-fonts",
      "id": "8eac7c4e-d473-5530-92ee-8cfaa7ee5e37",
      "name": "gatsby-plugin-prefetch-google-fonts",
      "version": "1.1.1",
      "pluginOptions": {
        "plugins": [],
        "fonts": [
          {
            "family": "Oswald",
            "subsets": [
              "latin"
            ]
          },
          {
            "family": "Open Sans",
            "variants": [
              "400",
              "700"
            ]
          },
          {
            "family": "Roboto"
          },
          {
            "family": "Playfair Display"
          },
          {
            "family": "Raleway"
          },
          {
            "family": "Rubik",
            "variants": [
              "300",
              "400",
              "500"
            ]
          }
        ]
      },
      "nodeAPIs": [
        "onPreBootstrap"
      ],
      "browserAPIs": [],
      "ssrAPIs": [
        "onRenderBody"
      ],
      "pluginFilepath": "/Users/macbook_pro/Documents/www/self/stefirkp.github.io/node_modules/gatsby-plugin-prefetch-google-fonts",
      "packageJson": {
        "name": "gatsby-plugin-prefetch-google-fonts",
        "description": "A Gatsby plugin to download and prefetch [Google Fonts](https://fonts.google.com/). Can increase performance as opposed to loading webfonts from Google's external stylesheet.",
        "version": "1.1.1",
        "main": "gatsby-ssr.js",
        "keywords": [
          "gatsby-plugin",
          "gatsby",
          "plugin",
          "web",
          "font",
          "loader",
          "google",
          "webfont",
          "webfontloader",
          "prefetch",
          "download",
          "downloader",
          "local"
        ],
        "author": {
          "name": "Kennedy Rose",
          "email": "krose@escaladesports.com"
        },
        "license": "MIT",
        "dependencies": [
          {
            "name": "@babel/runtime",
            "version": "^7.2.0"
          },
          {
            "name": "clean-css",
            "version": "^4.2.1"
          },
          {
            "name": "download",
            "version": "^7.1.0"
          },
          {
            "name": "fs-extra",
            "version": "^7.0.0"
          },
          {
            "name": "get-urls",
            "version": "^8.0.0"
          },
          {
            "name": "globby",
            "version": "^8.0.1"
          },
          {
            "name": "google-fonts-plugin",
            "version": "^2.0.2"
          },
          {
            "name": "object-hash",
            "version": "^1.3.0"
          }
        ],
        "devDependencies": [
          {
            "name": "@babel/cli",
            "version": "^7.1.2"
          },
          {
            "name": "@babel/core",
            "version": "^7.1.2"
          },
          {
            "name": "@babel/plugin-proposal-class-properties",
            "version": "^7.1.0"
          },
          {
            "name": "@babel/plugin-proposal-decorators",
            "version": "^7.1.2"
          },
          {
            "name": "@babel/plugin-proposal-do-expressions",
            "version": "^7.0.0"
          },
          {
            "name": "@babel/plugin-proposal-export-default-from",
            "version": "^7.0.0"
          },
          {
            "name": "@babel/plugin-proposal-export-namespace-from",
            "version": "^7.0.0"
          },
          {
            "name": "@babel/plugin-proposal-function-bind",
            "version": "^7.0.0"
          },
          {
            "name": "@babel/plugin-proposal-function-sent",
            "version": "^7.1.0"
          },
          {
            "name": "@babel/plugin-proposal-json-strings",
            "version": "^7.0.0"
          },
          {
            "name": "@babel/plugin-proposal-logical-assignment-operators",
            "version": "^7.0.0"
          },
          {
            "name": "@babel/plugin-proposal-nullish-coalescing-operator",
            "version": "^7.0.0"
          },
          {
            "name": "@babel/plugin-proposal-numeric-separator",
            "version": "^7.0.0"
          },
          {
            "name": "@babel/plugin-proposal-optional-chaining",
            "version": "^7.0.0"
          },
          {
            "name": "@babel/plugin-proposal-pipeline-operator",
            "version": "^7.0.0"
          },
          {
            "name": "@babel/plugin-proposal-throw-expressions",
            "version": "^7.0.0"
          },
          {
            "name": "@babel/plugin-syntax-dynamic-import",
            "version": "^7.0.0"
          },
          {
            "name": "@babel/plugin-syntax-import-meta",
            "version": "^7.0.0"
          },
          {
            "name": "@babel/plugin-syntax-jsx",
            "version": "^7.2.0"
          },
          {
            "name": "@babel/plugin-transform-runtime",
            "version": "^7.1.0"
          },
          {
            "name": "@babel/preset-env",
            "version": "^7.1.0"
          },
          {
            "name": "@babel/preset-react",
            "version": "^7.0.0"
          },
          {
            "name": "child-process-async",
            "version": "^1.0.1"
          },
          {
            "name": "child-process-promise",
            "version": "^2.2.1"
          },
          {
            "name": "emotion",
            "version": "^9.2.6"
          },
          {
            "name": "emotion-server",
            "version": "^9.2.6"
          },
          {
            "name": "enzyme",
            "version": "^3.5.0"
          },
          {
            "name": "enzyme-adapter-react-16",
            "version": "^1.3.0"
          },
          {
            "name": "eslint",
            "version": "^5.2.0"
          },
          {
            "name": "eslint-config-escalade-sports",
            "version": "^1.0.1"
          },
          {
            "name": "gatsby",
            "version": "^2.0.19"
          },
          {
            "name": "gatsby-plugin-emotion",
            "version": "2.0.5"
          },
          {
            "name": "husky",
            "version": "^0.14.3"
          },
          {
            "name": "identity-obj-proxy",
            "version": "^3.0.0"
          },
          {
            "name": "isomorphic-fetch",
            "version": "^2.2.1"
          },
          {
            "name": "jest",
            "version": "^23.4.2"
          },
          {
            "name": "jest-dom",
            "version": "^1.12.0"
          },
          {
            "name": "lint-staged",
            "version": "^7.2.0"
          },
          {
            "name": "netlify-cms",
            "version": "^1.9.3"
          },
          {
            "name": "netlify-lambda",
            "version": "^0.4.0"
          },
          {
            "name": "npm-run-all",
            "version": "^4.1.3"
          },
          {
            "name": "opn-cli",
            "version": "^3.1.0"
          },
          {
            "name": "react",
            "version": "^16.4.0"
          },
          {
            "name": "react-dom",
            "version": "^16.4.0"
          },
          {
            "name": "react-helmet",
            "version": "^5.2.0"
          },
          {
            "name": "react-netlify-form",
            "version": "^2.0.7"
          },
          {
            "name": "react-no-ssr",
            "version": "^1.1.0"
          },
          {
            "name": "react-test-renderer",
            "version": "^16.4.2"
          },
          {
            "name": "react-testing-library",
            "version": "^4.1.7"
          },
          {
            "name": "request",
            "version": "^2.87.0"
          },
          {
            "name": "statable",
            "version": "^0.3.2"
          },
          {
            "name": "static-server",
            "version": "^2.2.1"
          },
          {
            "name": "strip-html-comments",
            "version": "^1.0.0"
          },
          {
            "name": "toml",
            "version": "^2.3.3"
          },
          {
            "name": "wt-cli",
            "version": "^10.0.3"
          }
        ],
        "peerDependencies": [],
        "optionalDependecies": [],
        "bundledDependecies": []
      },
      "parent": "SOURCE",
      "children": [],
      "internal": {
        "contentDigest": "b7dc137afa7adef6fd6496c339a1e719",
        "type": "SitePlugin",
        "owner": "internal-data-bridge"
      }
    },
    "7374ebf2-d961-52ee-92a2-c25e7cb387a9": {
      "resolve": "/Users/macbook_pro/Documents/www/self/stefirkp.github.io",
      "id": "7374ebf2-d961-52ee-92a2-c25e7cb387a9",
      "name": "default-site-plugin",
      "version": "a0f3bd0aa485161da13b665d3adb8f3a",
      "pluginOptions": {
        "plugins": []
      },
      "nodeAPIs": [],
      "browserAPIs": [],
      "ssrAPIs": [],
      "pluginFilepath": "/Users/macbook_pro/Documents/www/self/stefirkp.github.io",
      "packageJson": {
        "name": "gatsby-starter-default",
        "description": "Gatsby default starter",
        "version": "1.0.0",
        "keywords": [
          "gatsby"
        ],
        "author": "Kyle Mathews <mathews.kyle@gmail.com>",
        "license": "MIT",
        "dependencies": [
          {
            "name": "gatsby",
            "version": "^2.0.53"
          },
          {
            "name": "gatsby-image",
            "version": "^2.0.20"
          },
          {
            "name": "gatsby-plugin-google-fonts",
            "version": "0.0.4"
          },
          {
            "name": "gatsby-plugin-manifest",
            "version": "^2.0.9"
          },
          {
            "name": "gatsby-plugin-offline",
            "version": "^2.0.16"
          },
          {
            "name": "gatsby-plugin-prefetch-google-fonts",
            "version": "^1.1.1"
          },
          {
            "name": "gatsby-plugin-react-helmet",
            "version": "^3.0.2"
          },
          {
            "name": "gatsby-plugin-sass",
            "version": "^2.0.7"
          },
          {
            "name": "gatsby-plugin-sharp",
            "version": "^2.0.15"
          },
          {
            "name": "gatsby-plugin-typography",
            "version": "^2.2.2"
          },
          {
            "name": "gatsby-source-filesystem",
            "version": "^2.0.8"
          },
          {
            "name": "gatsby-transformer-sharp",
            "version": "^2.1.8"
          },
          {
            "name": "node-sass",
            "version": "^4.11.0"
          },
          {
            "name": "prop-types",
            "version": "^15.6.2"
          },
          {
            "name": "react",
            "version": "^16.6.3"
          },
          {
            "name": "react-dom",
            "version": "^16.6.3"
          },
          {
            "name": "react-helmet",
            "version": "^5.2.0"
          },
          {
            "name": "react-typography",
            "version": "^0.16.18"
          },
          {
            "name": "typography",
            "version": "^0.16.18"
          }
        ],
        "devDependencies": [
          {
            "name": "gh-pages",
            "version": "^2.0.1"
          },
          {
            "name": "prettier",
            "version": "^1.15.2"
          }
        ],
        "peerDependencies": [],
        "optionalDependecies": [],
        "bundledDependecies": []
      },
      "parent": "SOURCE",
      "children": [],
      "internal": {
        "contentDigest": "59fd0cf60d57812b9945888b507a6022",
        "type": "SitePlugin",
        "owner": "internal-data-bridge"
      }
    },
    "3c1b514a-cada-58bd-a809-ba978ced4fa9": {
      "resolve": "/Users/macbook_pro/Documents/www/self/stefirkp.github.io/node_modules/gatsby-plugin-page-creator",
      "id": "3c1b514a-cada-58bd-a809-ba978ced4fa9",
      "name": "gatsby-plugin-page-creator",
      "version": "2.0.4",
      "pluginOptions": {
        "plugins": [],
        "path": "/Users/macbook_pro/Documents/www/self/stefirkp.github.io/src/pages",
        "pathCheck": false
      },
      "nodeAPIs": [
        "createPagesStatefully"
      ],
      "browserAPIs": [],
      "ssrAPIs": [],
      "pluginFilepath": "/Users/macbook_pro/Documents/www/self/stefirkp.github.io/node_modules/gatsby-plugin-page-creator",
      "packageJson": {
        "name": "gatsby-plugin-page-creator",
        "description": "Gatsby plugin that automatically creates pages from React components in specified directories",
        "version": "2.0.4",
        "main": "index.js",
        "keywords": [
          "gatsby",
          "gatsby-plugin"
        ],
        "author": {
          "name": "Kyle Mathews",
          "email": "mathews.kyle@gmail.com"
        },
        "license": "MIT",
        "dependencies": [
          {
            "name": "@babel/runtime",
            "version": "^7.0.0"
          },
          {
            "name": "bluebird",
            "version": "^3.5.0"
          },
          {
            "name": "chokidar",
            "version": "^1.7.0"
          },
          {
            "name": "fs-exists-cached",
            "version": "^1.0.0"
          },
          {
            "name": "glob",
            "version": "^7.1.1"
          },
          {
            "name": "lodash",
            "version": "^4.17.10"
          },
          {
            "name": "micromatch",
            "version": "^3.1.10"
          },
          {
            "name": "parse-filepath",
            "version": "^1.0.1"
          },
          {
            "name": "slash",
            "version": "^1.0.0"
          }
        ],
        "devDependencies": [
          {
            "name": "@babel/cli",
            "version": "^7.0.0"
          },
          {
            "name": "@babel/core",
            "version": "^7.0.0"
          },
          {
            "name": "babel-preset-gatsby-package",
            "version": "^0.1.2"
          },
          {
            "name": "cross-env",
            "version": "^5.0.5"
          }
        ],
        "peerDependencies": [
          {
            "name": "gatsby",
            "version": ">2.0.0-alpha"
          }
        ],
        "optionalDependecies": [],
        "bundledDependecies": []
      },
      "parent": "SOURCE",
      "children": [],
      "internal": {
        "contentDigest": "c88cb26247b1d677fd701b1c4b1aedd8",
        "type": "SitePlugin",
        "owner": "internal-data-bridge"
      }
    },
    "Site": {
      "siteMetadata": {
        "title": "Title from siteMetadata",
        "description": "Kick off your next, great Gatsby project with this default starter. This barebones starter ships with the main Gatsby configuration files you might need.",
        "author": "@gatsbyjs"
      },
      "pathPrefix": "/stefirkp.github.io",
      "polyfill": true,
      "buildTime": "2019-01-11T15:38:52.243Z",
      "id": "Site",
      "parent": "SOURCE",
      "children": [],
      "internal": {
        "contentDigest": "1f1db6eda95879d47aa201d098faa645",
        "type": "Site",
        "owner": "internal-data-bridge"
      }
    },
    "2d4dd647-09d8-5971-9477-9d197dd622e2": {
      "id": "2d4dd647-09d8-5971-9477-9d197dd622e2",
      "children": [],
      "parent": "___SOURCE___",
      "internal": {
        "contentDigest": "6b39c29d47b0de809cb993e90c997348",
        "type": "Directory",
        "description": "Directory \"src/images\"",
        "owner": "gatsby-source-filesystem"
      },
      "sourceInstanceName": "images",
      "absolutePath": "/Users/macbook_pro/Documents/www/self/stefirkp.github.io/src/images",
      "relativePath": "",
      "extension": "",
      "size": 288,
      "prettySize": "288 B",
      "modifiedTime": "2018-12-18T14:54:25.772Z",
      "accessTime": "2019-01-11T15:39:02.742Z",
      "changeTime": "2019-01-11T15:37:22.642Z",
      "birthTime": "2018-12-17T08:30:16.017Z",
      "root": "/",
      "dir": "/Users/macbook_pro/Documents/www/self/stefirkp.github.io/src",
      "base": "images",
      "ext": "",
      "name": "images",
      "relativeDirectory": "..",
      "dev": 16777220,
      "mode": 16877,
      "nlink": 9,
      "uid": 501,
      "gid": 20,
      "rdev": 0,
      "blksize": 4096,
      "ino": 12887572331,
      "blocks": 0,
      "atimeMs": 1547221142742.4248,
      "mtimeMs": 1545144865772.3108,
      "ctimeMs": 1547221042641.6213,
      "birthtimeMs": 1545035416016.7283,
      "atime": "2019-01-11T15:39:02.742Z",
      "mtime": "2018-12-18T14:54:25.772Z",
      "ctime": "2019-01-11T15:37:22.642Z",
      "birthtime": "2018-12-17T08:30:16.017Z"
    },
    "d455ad0b-b43e-5d83-a695-82efb9b088ef": {
      "id": "d455ad0b-b43e-5d83-a695-82efb9b088ef",
      "children": [
        "16899813-5347-5616-b813-147a66ab86df"
      ],
      "parent": "___SOURCE___",
      "internal": {
        "contentDigest": "4a9773549091c227cd2eb82ccd9c5e3a",
        "type": "File",
        "mediaType": "image/png",
        "description": "File \"src/images/gatsby-icon.png\"",
        "owner": "gatsby-source-filesystem"
      },
      "sourceInstanceName": "images",
      "absolutePath": "/Users/macbook_pro/Documents/www/self/stefirkp.github.io/src/images/gatsby-icon.png",
      "relativePath": "gatsby-icon.png",
      "extension": "png",
      "size": 21212,
      "prettySize": "21.2 kB",
      "modifiedTime": "2018-12-17T08:30:16.018Z",
      "accessTime": "2019-01-11T15:38:27.832Z",
      "changeTime": "2019-01-11T15:37:22.594Z",
      "birthTime": "2018-12-17T08:30:16.018Z",
      "root": "/",
      "dir": "/Users/macbook_pro/Documents/www/self/stefirkp.github.io/src/images",
      "base": "gatsby-icon.png",
      "ext": ".png",
      "name": "gatsby-icon",
      "relativeDirectory": "",
      "dev": 16777220,
      "mode": 33188,
      "nlink": 1,
      "uid": 501,
      "gid": 20,
      "rdev": 0,
      "blksize": 4096,
      "ino": 12887572334,
      "blocks": 48,
      "atimeMs": 1547221107832.326,
      "mtimeMs": 1545035416018.0935,
      "ctimeMs": 1547221042593.5093,
      "birthtimeMs": 1545035416017.899,
      "atime": "2019-01-11T15:38:27.832Z",
      "mtime": "2018-12-17T08:30:16.018Z",
      "ctime": "2019-01-11T15:37:22.594Z",
      "birthtime": "2018-12-17T08:30:16.018Z"
    },
    "16899813-5347-5616-b813-147a66ab86df": {
      "id": "16899813-5347-5616-b813-147a66ab86df",
      "children": [],
      "parent": "d455ad0b-b43e-5d83-a695-82efb9b088ef",
      "internal": {
        "contentDigest": "4a9773549091c227cd2eb82ccd9c5e3a",
        "type": "ImageSharp",
        "owner": "gatsby-transformer-sharp"
      }
    },
    "2c322085-92ec-5112-88c4-bc668979d06c": {
      "id": "2c322085-92ec-5112-88c4-bc668979d06c",
      "children": [
        "5920e217-10ef-50e1-8060-8a83ce3ee4d7"
      ],
      "parent": "___SOURCE___",
      "internal": {
        "contentDigest": "6d91c86c0fde632ba4cd01062fd9ccfa",
        "type": "File",
        "mediaType": "image/png",
        "description": "File \"src/images/gatsby-astronaut.png\"",
        "owner": "gatsby-source-filesystem"
      },
      "sourceInstanceName": "images",
      "absolutePath": "/Users/macbook_pro/Documents/www/self/stefirkp.github.io/src/images/gatsby-astronaut.png",
      "relativePath": "gatsby-astronaut.png",
      "extension": "png",
      "size": 167273,
      "prettySize": "167 kB",
      "modifiedTime": "2018-12-17T08:30:16.018Z",
      "accessTime": "2019-01-11T15:38:27.832Z",
      "changeTime": "2019-01-11T15:37:22.590Z",
      "birthTime": "2018-12-17T08:30:16.017Z",
      "root": "/",
      "dir": "/Users/macbook_pro/Documents/www/self/stefirkp.github.io/src/images",
      "base": "gatsby-astronaut.png",
      "ext": ".png",
      "name": "gatsby-astronaut",
      "relativeDirectory": "",
      "dev": 16777220,
      "mode": 33188,
      "nlink": 1,
      "uid": 501,
      "gid": 20,
      "rdev": 0,
      "blksize": 4096,
      "ino": 12887572333,
      "blocks": 328,
      "atimeMs": 1547221107832.3284,
      "mtimeMs": 1545035416017.7651,
      "ctimeMs": 1547221042590.0593,
      "birthtimeMs": 1545035416016.7803,
      "atime": "2019-01-11T15:38:27.832Z",
      "mtime": "2018-12-17T08:30:16.018Z",
      "ctime": "2019-01-11T15:37:22.590Z",
      "birthtime": "2018-12-17T08:30:16.017Z"
    },
    "5920e217-10ef-50e1-8060-8a83ce3ee4d7": {
      "id": "5920e217-10ef-50e1-8060-8a83ce3ee4d7",
      "children": [],
      "parent": "2c322085-92ec-5112-88c4-bc668979d06c",
      "internal": {
        "contentDigest": "6d91c86c0fde632ba4cd01062fd9ccfa",
        "type": "ImageSharp",
        "owner": "gatsby-transformer-sharp"
      }
    },
    "ca32608c-b2c7-54bb-ab91-6b6a42dd7173": {
      "id": "ca32608c-b2c7-54bb-ab91-6b6a42dd7173",
      "children": [
        "6b4ac07f-3846-5b11-8c3a-d166a69aa44d"
      ],
      "parent": "___SOURCE___",
      "internal": {
        "contentDigest": "5f93bfa6f9350123b55d5522eb7543dc",
        "type": "File",
        "mediaType": "image/png",
        "description": "File \"src/images/a.png\"",
        "owner": "gatsby-source-filesystem"
      },
      "sourceInstanceName": "images",
      "absolutePath": "/Users/macbook_pro/Documents/www/self/stefirkp.github.io/src/images/a.png",
      "relativePath": "a.png",
      "extension": "png",
      "size": 326599,
      "prettySize": "327 kB",
      "modifiedTime": "2018-12-18T13:03:24.677Z",
      "accessTime": "2019-01-11T15:38:27.832Z",
      "changeTime": "2019-01-11T15:37:22.640Z",
      "birthTime": "2018-12-18T13:03:24.677Z",
      "root": "/",
      "dir": "/Users/macbook_pro/Documents/www/self/stefirkp.github.io/src/images",
      "base": "a.png",
      "ext": ".png",
      "name": "a",
      "relativeDirectory": "",
      "dev": 16777220,
      "mode": 33188,
      "nlink": 1,
      "uid": 501,
      "gid": 20,
      "rdev": 0,
      "blksize": 4096,
      "ino": 12887572337,
      "blocks": 640,
      "atimeMs": 1547221107832.3154,
      "mtimeMs": 1545138204677.0166,
      "ctimeMs": 1547221042639.941,
      "birthtimeMs": 1545138204676.6694,
      "atime": "2019-01-11T15:38:27.832Z",
      "mtime": "2018-12-18T13:03:24.677Z",
      "ctime": "2019-01-11T15:37:22.640Z",
      "birthtime": "2018-12-18T13:03:24.677Z"
    },
    "6b4ac07f-3846-5b11-8c3a-d166a69aa44d": {
      "id": "6b4ac07f-3846-5b11-8c3a-d166a69aa44d",
      "children": [],
      "parent": "ca32608c-b2c7-54bb-ab91-6b6a42dd7173",
      "internal": {
        "contentDigest": "5f93bfa6f9350123b55d5522eb7543dc",
        "type": "ImageSharp",
        "owner": "gatsby-transformer-sharp"
      }
    },
    "0d3905ff-e45b-57a9-a880-cb9f8a6150ef": {
      "id": "0d3905ff-e45b-57a9-a880-cb9f8a6150ef",
      "children": [
        "6b35247a-ec88-5639-b0c7-5d21eb6bc216"
      ],
      "parent": "___SOURCE___",
      "internal": {
        "contentDigest": "8b6b2026da34fbd13a5bb83ad3db14d8",
        "type": "File",
        "mediaType": "image/png",
        "description": "File \"src/images/c.png\"",
        "owner": "gatsby-source-filesystem"
      },
      "sourceInstanceName": "images",
      "absolutePath": "/Users/macbook_pro/Documents/www/self/stefirkp.github.io/src/images/c.png",
      "relativePath": "c.png",
      "extension": "png",
      "size": 480354,
      "prettySize": "480 kB",
      "modifiedTime": "2018-12-18T13:03:12.947Z",
      "accessTime": "2019-01-11T15:38:27.832Z",
      "changeTime": "2019-01-11T15:37:22.598Z",
      "birthTime": "2018-12-18T13:03:12.947Z",
      "root": "/",
      "dir": "/Users/macbook_pro/Documents/www/self/stefirkp.github.io/src/images",
      "base": "c.png",
      "ext": ".png",
      "name": "c",
      "relativeDirectory": "",
      "dev": 16777220,
      "mode": 33188,
      "nlink": 1,
      "uid": 501,
      "gid": 20,
      "rdev": 0,
      "blksize": 4096,
      "ino": 12887572336,
      "blocks": 944,
      "atimeMs": 1547221107832.3198,
      "mtimeMs": 1545138192947.1216,
      "ctimeMs": 1547221042598.1267,
      "birthtimeMs": 1545138192946.784,
      "atime": "2019-01-11T15:38:27.832Z",
      "mtime": "2018-12-18T13:03:12.947Z",
      "ctime": "2019-01-11T15:37:22.598Z",
      "birthtime": "2018-12-18T13:03:12.947Z"
    },
    "6b35247a-ec88-5639-b0c7-5d21eb6bc216": {
      "id": "6b35247a-ec88-5639-b0c7-5d21eb6bc216",
      "children": [],
      "parent": "0d3905ff-e45b-57a9-a880-cb9f8a6150ef",
      "internal": {
        "contentDigest": "8b6b2026da34fbd13a5bb83ad3db14d8",
        "type": "ImageSharp",
        "owner": "gatsby-transformer-sharp"
      }
    },
    "3cf4a62d-427c-5f6e-8599-8354214d8a77": {
      "id": "3cf4a62d-427c-5f6e-8599-8354214d8a77",
      "children": [
        "db1f7abb-970e-5675-b6b6-8022facf28e3"
      ],
      "parent": "___SOURCE___",
      "internal": {
        "contentDigest": "d6a70286d865158797a4287627b6bec3",
        "type": "File",
        "mediaType": "image/png",
        "description": "File \"src/images/b.png\"",
        "owner": "gatsby-source-filesystem"
      },
      "sourceInstanceName": "images",
      "absolutePath": "/Users/macbook_pro/Documents/www/self/stefirkp.github.io/src/images/b.png",
      "relativePath": "b.png",
      "extension": "png",
      "size": 612340,
      "prettySize": "612 kB",
      "modifiedTime": "2018-12-18T13:02:59.644Z",
      "accessTime": "2019-01-11T15:38:27.832Z",
      "changeTime": "2019-01-11T15:37:22.596Z",
      "birthTime": "2018-12-18T13:02:59.644Z",
      "root": "/",
      "dir": "/Users/macbook_pro/Documents/www/self/stefirkp.github.io/src/images",
      "base": "b.png",
      "ext": ".png",
      "name": "b",
      "relativeDirectory": "",
      "dev": 16777220,
      "mode": 33188,
      "nlink": 1,
      "uid": 501,
      "gid": 20,
      "rdev": 0,
      "blksize": 4096,
      "ino": 12887572335,
      "blocks": 1200,
      "atimeMs": 1547221107832.323,
      "mtimeMs": 1545138179644.4192,
      "ctimeMs": 1547221042595.7786,
      "birthtimeMs": 1545138179644.149,
      "atime": "2019-01-11T15:38:27.832Z",
      "mtime": "2018-12-18T13:02:59.644Z",
      "ctime": "2019-01-11T15:37:22.596Z",
      "birthtime": "2018-12-18T13:02:59.644Z"
    },
    "db1f7abb-970e-5675-b6b6-8022facf28e3": {
      "id": "db1f7abb-970e-5675-b6b6-8022facf28e3",
      "children": [],
      "parent": "3cf4a62d-427c-5f6e-8599-8354214d8a77",
      "internal": {
        "contentDigest": "d6a70286d865158797a4287627b6bec3",
        "type": "ImageSharp",
        "owner": "gatsby-transformer-sharp"
      }
    },
    "6035962c-59d3-507e-9242-f470a9d1d84d": {
      "id": "6035962c-59d3-507e-9242-f470a9d1d84d",
      "children": [
        "d1743d9a-6eb1-5367-88fe-466bc4197650"
      ],
      "parent": "___SOURCE___",
      "internal": {
        "contentDigest": "6223f894b7bfa9d18d4afdbe2d63e4be",
        "type": "File",
        "mediaType": "image/png",
        "description": "File \"src/images/d.png\"",
        "owner": "gatsby-source-filesystem"
      },
      "sourceInstanceName": "images",
      "absolutePath": "/Users/macbook_pro/Documents/www/self/stefirkp.github.io/src/images/d.png",
      "relativePath": "d.png",
      "extension": "png",
      "size": 582450,
      "prettySize": "582 kB",
      "modifiedTime": "2018-12-18T13:03:18.555Z",
      "accessTime": "2019-01-11T15:38:27.832Z",
      "changeTime": "2019-01-11T15:37:22.641Z",
      "birthTime": "2018-12-18T13:03:18.555Z",
      "root": "/",
      "dir": "/Users/macbook_pro/Documents/www/self/stefirkp.github.io/src/images",
      "base": "d.png",
      "ext": ".png",
      "name": "d",
      "relativeDirectory": "",
      "dev": 16777220,
      "mode": 33188,
      "nlink": 1,
      "uid": 501,
      "gid": 20,
      "rdev": 0,
      "blksize": 4096,
      "ino": 12887572338,
      "blocks": 1144,
      "atimeMs": 1547221107832.31,
      "mtimeMs": 1545138198555.3677,
      "ctimeMs": 1547221042641.4924,
      "birthtimeMs": 1545138198554.8108,
      "atime": "2019-01-11T15:38:27.832Z",
      "mtime": "2018-12-18T13:03:18.555Z",
      "ctime": "2019-01-11T15:37:22.641Z",
      "birthtime": "2018-12-18T13:03:18.555Z"
    },
    "d1743d9a-6eb1-5367-88fe-466bc4197650": {
      "id": "d1743d9a-6eb1-5367-88fe-466bc4197650",
      "children": [],
      "parent": "6035962c-59d3-507e-9242-f470a9d1d84d",
      "internal": {
        "contentDigest": "6223f894b7bfa9d18d4afdbe2d63e4be",
        "type": "ImageSharp",
        "owner": "gatsby-transformer-sharp"
      }
    },
    "SitePage /404/": {
      "jsonName": "404-22d",
      "internalComponentName": "Component404",
      "path": "/404/",
      "component": "/Users/macbook_pro/Documents/www/self/stefirkp.github.io/src/pages/404.js",
      "componentChunkName": "component---src-pages-404-js",
      "context": {},
      "pluginCreator___NODE": "3c1b514a-cada-58bd-a809-ba978ced4fa9",
      "pluginCreatorId": "3c1b514a-cada-58bd-a809-ba978ced4fa9",
      "componentPath": "/Users/macbook_pro/Documents/www/self/stefirkp.github.io/src/pages/404.js",
      "id": "SitePage /404/",
      "parent": "SOURCE",
      "children": [],
      "internal": {
        "type": "SitePage",
        "contentDigest": "376f94ad960c0908a77522d6bc5875ef",
        "description": "3c1b514a-cada-58bd-a809-ba978ced4fa9",
        "owner": "internal-data-bridge"
      }
    },
    "SitePage /": {
      "jsonName": "index",
      "internalComponentName": "ComponentIndex",
      "path": "/",
      "component": "/Users/macbook_pro/Documents/www/self/stefirkp.github.io/src/pages/index.js",
      "componentChunkName": "component---src-pages-index-js",
      "context": {},
      "pluginCreator___NODE": "3c1b514a-cada-58bd-a809-ba978ced4fa9",
      "pluginCreatorId": "3c1b514a-cada-58bd-a809-ba978ced4fa9",
      "componentPath": "/Users/macbook_pro/Documents/www/self/stefirkp.github.io/src/pages/index.js",
      "id": "SitePage /",
      "parent": "SOURCE",
      "children": [],
      "internal": {
        "type": "SitePage",
        "contentDigest": "b56871e37c4f83b949261320e2687326",
        "description": "3c1b514a-cada-58bd-a809-ba978ced4fa9",
        "owner": "internal-data-bridge"
      }
    },
    "SitePage /404.html": {
      "jsonName": "404-html-516",
      "internalComponentName": "Component404Html",
      "path": "/404.html",
      "component": "/Users/macbook_pro/Documents/www/self/stefirkp.github.io/src/pages/404.js",
      "componentChunkName": "component---src-pages-404-js",
      "context": {},
      "pluginCreator___NODE": "f795702c-a3b8-5a88-88ee-5d06019d44fa",
      "pluginCreatorId": "f795702c-a3b8-5a88-88ee-5d06019d44fa",
      "componentPath": "/Users/macbook_pro/Documents/www/self/stefirkp.github.io/src/pages/404.js",
      "id": "SitePage /404.html",
      "parent": "SOURCE",
      "children": [],
      "internal": {
        "type": "SitePage",
        "contentDigest": "5c56d8b52b339ec131ec1c85e0023ae2",
        "description": "f795702c-a3b8-5a88-88ee-5d06019d44fa",
        "owner": "internal-data-bridge"
      }
    }
  },
  "status": {
    "plugins": {},
    "PLUGINS_HASH": "f058203eca2ddbcd3ead6d68215a403b"
  },
  "componentDataDependencies": {
    "nodes": {
      "Site": [
        "sq--src-components-layout-js",
        "sq--src-components-seo-js"
      ],
      "2c322085-92ec-5112-88c4-bc668979d06c": [
        "sq--src-components-image-js"
      ],
      "5920e217-10ef-50e1-8060-8a83ce3ee4d7": [
        "sq--src-components-image-js"
      ]
    },
    "connections": {}
  },
  "jsonDataPaths": {
    "404-22d": "44/path---404-22-d-bce-NZuapzHg3X9TaN1iIixfv1W23E",
    "sq--src-components-layout-js": 755544856,
    "sq--src-components-seo-js": 1025518380,
    "index": "173/path---index-6a9-NZuapzHg3X9TaN1iIixfv1W23E",
    "404-html-516": "164/path---404-html-516-62a-NZuapzHg3X9TaN1iIixfv1W23E",
    "sq--src-components-image-js": 2011440971
  },
  "components": {
    "/Users/macbook_pro/Documents/www/self/stefirkp.github.io/src/pages/404.js": {
      "query": "",
      "componentPath": "/Users/macbook_pro/Documents/www/self/stefirkp.github.io/src/pages/404.js"
    },
    "/Users/macbook_pro/Documents/www/self/stefirkp.github.io/src/pages/index.js": {
      "query": "",
      "componentPath": "/Users/macbook_pro/Documents/www/self/stefirkp.github.io/src/pages/index.js"
    }
  },
  "staticQueryComponents": {
    "sq--src-components-image-js": {
      "name": "usersMacbookProDocumentsWwwSelfStefirkpGithubIoSrcComponentsImageJs2011440971",
      "componentPath": "/Users/macbook_pro/Documents/www/self/stefirkp.github.io/src/components/image.js",
      "id": "sq--src-components-image-js",
      "jsonName": "sq--src-components-image-js",
      "query": "query usersMacbookProDocumentsWwwSelfStefirkpGithubIoSrcComponentsImageJs2011440971 {\n  placeholderImage: file(relativePath: {eq: \"gatsby-astronaut.png\"}) {\n    childImageSharp {\n      fluid(maxWidth: 300) {\n        ...GatsbyImageSharpFluid\n      }\n    }\n  }\n}\n\nfragment GatsbyImageSharpFluid on ImageSharpFluid {\n  base64\n  aspectRatio\n  src\n  srcSet\n  sizes\n}\n",
      "hash": 2011440971
    },
    "sq--src-components-layout-js": {
      "name": "SiteTitleQuery",
      "componentPath": "/Users/macbook_pro/Documents/www/self/stefirkp.github.io/src/components/layout.js",
      "id": "sq--src-components-layout-js",
      "jsonName": "sq--src-components-layout-js",
      "query": "query SiteTitleQuery {\n  site {\n    siteMetadata {\n      title\n    }\n  }\n}\n",
      "hash": 755544856
    },
    "sq--src-components-seo-js": {
      "name": "DefaultSEOQuery",
      "componentPath": "/Users/macbook_pro/Documents/www/self/stefirkp.github.io/src/components/seo.js",
      "id": "sq--src-components-seo-js",
      "jsonName": "sq--src-components-seo-js",
      "query": "query DefaultSEOQuery {\n  site {\n    siteMetadata {\n      title\n      description\n      author\n    }\n  }\n}\n",
      "hash": 1025518380
    }
  }
}